src/__init__.py
src/logging_config.py
src/prompts.py
src/resources.py
src/server.py
src/core/__init__.py
src/core/abacus_runner.py
src/tools/__init__.py
src/tools/calculation_execution.py
src/tools/intelligent_assistant.py
src/tools/property_analysis.py
src/tools/result_interpreter.py
src/tools/structure_management.py
src/tools/task_management.py
iflow_mcp_phelanshao_abacus_mcp_server-0.1.0.dist-info/METADATA
iflow_mcp_phelanshao_abacus_mcp_server-0.1.0.dist-info/WHEEL
iflow_mcp_phelanshao_abacus_mcp_server-0.1.0.dist-info/entry_points.txt
iflow_mcp_phelanshao_abacus_mcp_server-0.1.0.dist-info/licenses/LICENSE
iflow_mcp_phelanshao_abacus_mcp_server-0.1.0.dist-info/RECORD
