Metadata-Version: 2.4
Name: iflow-mcp_phelanshao_abacus-mcp-server
Version: 0.1.0
Summary: A Model Context Protocol server for ABACUS first-principles calculations
Project-URL: Homepage, https://github.com/iflow-mcp/abacus-mcp-server
Project-URL: Repository, https://github.com/iflow-mcp/abacus-mcp-server
Project-URL: Documentation, https://abacus-mcp-server.readthedocs.io/
Project-URL: Bug Reports, https://github.com/iflow-mcp/abacus-mcp-server/issues
Project-URL: ABACUS Official, https://abacus.deepmodeling.com/
Author-email: phelanshao <contact@example.com>
License: MIT
License-File: LICENSE
Keywords: abacus,dft,first-principles,materials-science,mcp,quantum-chemistry
Classifier: Development Status :: 4 - Beta
Classifier: Intended Audience :: Science/Research
Classifier: License :: OSI Approved :: MIT License
Classifier: Operating System :: OS Independent
Classifier: Programming Language :: Python :: 3
Classifier: Programming Language :: Python :: 3.8
Classifier: Programming Language :: Python :: 3.9
Classifier: Programming Language :: Python :: 3.10
Classifier: Programming Language :: Python :: 3.11
Classifier: Topic :: Scientific/Engineering :: Chemistry
Classifier: Topic :: Scientific/Engineering :: Physics
Requires-Python: >=3.8
Requires-Dist: ase>=3.22.0
Requires-Dist: fastmcp>=0.1.0
Requires-Dist: numpy>=1.21.0
Requires-Dist: psutil>=5.8.0
Requires-Dist: pydantic>=2.0.0
Requires-Dist: python-json-logger>=2.0.0
Requires-Dist: scipy>=1.7.0
